app/__init__.py
app/cli.py
app/core/__init__.py
app/core/config.py
app/core/invoke/__init__.py
app/core/invoke/generator_hive_reward.py
app/core/invoke/generator_hive_reward_from_url.py
app/core/invoke/io/__init__.py
app/core/invoke/io/reader.py
app/core/llm/__init__.py
app/core/llm/agent_hive_reward_generator.py
app/core/llm/data_structure/__init__.py
app/core/llm/data_structure/reward_data_json.py
app/core/llm/front_layer/__init__.py
app/core/llm/front_layer/slice.py
app/core/llm/old/__init__.py
app/core/llm/old/report_sum.py
app/core/llm/rear_layer/__init__.py
app/core/scheduler/__init__.py
app/core/scheduler/agentManager.py
app/core/scheduler/agent_scheduler_manager.py
app/core/scheduler/core/__init__.py
app/core/scheduler/core/init.py
app/core/scheduler/core/schemas/__init__.py
app/core/scheduler/core/schemas/schemas.py
app/core/scheduler/core/schemas/works/PydanticSafetyParser.py
app/core/scheduler/core/schemas/works/__init__.py
app/core/scheduler/toolschain/__init__.py
app/core/scheduler/toolschain/tools_manager.py
app/core/validator/__init__.py
app/core/validator/hive_reward_parser.py
app/core/validator/hive_reward_validator.py
app/core/validator/valid_hive_reward_json.py
app/core/validator/article_generator/__init__.py
app/core/validator/article_generator/random_article_generator.py
tools/__init__.py
tools/args_wrap/__init__.py
tools/args_wrap/apend_doc.py
tools/args_wrap/args_wraper.py
tools/func/__init__.py
tools/func/result_tidy_up.py
tools/func/retry_decorator.py
tools/ini/__init__.py
tools/ini/iniworker.py
hive_reward_generator-0.1.dev3.dist-info/METADATA
hive_reward_generator-0.1.dev3.dist-info/WHEEL
hive_reward_generator-0.1.dev3.dist-info/entry_points.txt
hive_reward_generator-0.1.dev3.dist-info/top_level.txt
hive_reward_generator-0.1.dev3.dist-info/RECORD
