Metadata-Version: 2.4
Name: hive-reward-generator
Version: 0.1.dev3
Summary: A dataset container for al-1s project.
Author-email: stupidfish001 <shovel@hscsec.cn>
Classifier: Programming Language :: Python :: 3
Classifier: License :: OSI Approved :: MIT License
Classifier: Operating System :: OS Independent
Requires-Python: >=3.6
Requires-Dist: typer==0.15.3
Requires-Dist: click==8.1.8
Requires-Dist: kink
Requires-Dist: loguru
Requires-Dist: pandas
Requires-Dist: pyarrow
Requires-Dist: pydantic
Requires-Dist: langchain-openai
Requires-Dist: langchain
Requires-Dist: tqdm
Requires-Dist: transformers
Requires-Dist: torch
